singletCode/__init__.py
singletCode/count_doublets_utils_copy.py
singletCode/general_utility_functions.py
singletCode/get_singlets.py
singletCode-1.1.0.dist-info/LICENSE
singletCode-1.1.0.dist-info/METADATA
singletCode-1.1.0.dist-info/WHEEL
singletCode-1.1.0.dist-info/top_level.txt
singletCode-1.1.0.dist-info/RECORD
