Metadata-Version: 2.1
Name: singletCode
Version: 1.1.0
Summary: singletCode is a package to identify true singlets in lineage-barcoded sequencing data.
Author-email: Keerthana M Arun <keerthana.melekotearun@northwestern.edu>, Ziyang Zhang <ziyang.zhang1@northwestern.edu>
License: BSD 3-Clause License
Project-URL: Homepage, https://goyallab.github.io/SingletCodeWebsite/
Project-URL: Documentation, https://goyallab.github.io/SingletCodeWebsite/
Classifier: Programming Language :: Python :: 3
Classifier: License :: OSI Approved :: BSD License
Classifier: Intended Audience :: Science/Research
Classifier: Operating System :: OS Independent
Classifier: Topic :: Scientific/Engineering
Classifier: Topic :: Scientific/Engineering :: Bio-Informatics
Requires-Python: >=3.7
License-File: LICENSE
Requires-Dist: scipy >=1.1.0
Requires-Dist: pandas >=0.23.4
Requires-Dist: tqdm >=4.28.1
Requires-Dist: matplotlib >=3.0.2
